README.md
setup.py
pyvida/__init__.py
pyvida/achievements.py
pyvida/action.py
pyvida/actor.py
pyvida/camera.py
pyvida/collection.py
pyvida/constants.py
pyvida/editor.py
pyvida/emitter.py
pyvida/factory.py
pyvida/game.py
pyvida/graphics.py
pyvida/io.py
pyvida/menufactory.py
pyvida/menumanager.py
pyvida/motion.py
pyvida/motiondelta.py
pyvida/motionmanager.py
pyvida/portal.py
pyvida/runner.py
pyvida/scene.py
pyvida/settings.py
pyvida/sound.py
pyvida/sprite.py
pyvida/text.py
pyvida/utils.py
pyvida/walkareamanager.py
pyvida.egg-info/PKG-INFO
pyvida.egg-info/SOURCES.txt
pyvida.egg-info/dependency_links.txt
pyvida.egg-info/requires.txt
pyvida.egg-info/top_level.txt