Metadata-Version: 2.1
Name: pyvida
Version: 7.0.0
Summary: Cross platform point-and-click 2D adventure game engine
Home-page: https://github.com/dodgyville/pyvida
Author: Luke Miller
Author-email: dodgyville@gmail.com
License: UNKNOWN
Platform: UNKNOWN
Classifier: Programming Language :: Python :: 3
Classifier: License :: OSI Approved :: MIT License
Classifier: Operating System :: OS Independent
